KorToBraille/KorToBraille.py
KorToBraille/NumberFunc.py
KorToBraille/PunctuationFunc.py
KorToBraille/__init__.py
KorToBraille/data.py
kortobraille-1.0.2.dist-info/METADATA
kortobraille-1.0.2.dist-info/WHEEL
kortobraille-1.0.2.dist-info/licenses/LICENSE.txt
kortobraille-1.0.2.dist-info/RECORD
